
{
  "metadata": {
    "version": 4.5,
    "type": "Object",
    "generator": "Object3D.toJSON"
  },

  "object": {
    "uuid": "E2F101D3-1E1D-431E-A3C8-59B72088C385",
    "type": "Scene",
    "name": "Scene",
    "layers": 1,
    "matrix": [1,0,0,0,0,1,0,0,0,0,1,0,0,0,0,1],
    "children": [
      {
        "uuid": "F539FEC9-8A56-4285-9906-866C948DB8A1",
        "type": "AmbientLight",
        "name": "AmbientLight",
        "layers": 1,
        "matrix": [1,0,0,0,0,1,0,0,0,0,1,0,0,25.380197,0,1],
        "color": 16777215,
        "intensity": 0.7
      },
      {
        "uuid": "ACC6D81A-BD9E-4F55-9341-BCE3A87B79A7",
        "type": "PointLight",
        "name": "PointLight",
        "castShadow": true,
        "layers": 1,
        "matrix": [1,0,0,0,0,1,0,0,0,0,1,0,-21.160228,19.649872,-34.553626,1],
        "color": 16759773,
        "intensity": 0.24,
        "distance": 0,
        "decay": 0,
        "shadow": {
          "radius": 6.6,
          "camera": {
            "uuid": "E3BD03B8-0FCD-4D7A-BCED-C1BF6F7F2612",
            "type": "PerspectiveCamera",
            "layers": 1,
            "fov": 90,
            "zoom": 1,
            "near": 0.5,
            "far": 500,
            "focus": 10,
            "aspect": 1,
            "filmGauge": 35,
            "filmOffset": 0
          }
        }
      },
      {
        "uuid": "2B7FBA11-0486-4A24-9B80-4E0C383243C4",
        "type": "SpotLight",
        "name": "SpotLight",
        "castShadow": true,
        "layers": 1,
        "matrix": [1,0,0,0,0,1,0,0,0,0,1,0,14.610886,27.598,43.659,1],
        "color": 65535,
        "intensity": 2.42,
        "distance": 93.42,
        "angle": 0.814,
        "decay": 1.16,
        "penumbra": 0.78,
        "shadow": {
          "radius": 3.18,
          "camera": {
            "uuid": "C4556FAD-B269-4AAE-BC07-BA9D208BD0A1",
            "type": "PerspectiveCamera",
            "layers": 1,
            "fov": 50,
            "zoom": 1,
            "near": 0.5,
            "far": 500,
            "focus": 10,
            "aspect": 1,
            "filmGauge": 35,
            "filmOffset": 0
          }
        }
      },
      {
        "uuid": "B0AEE5AD-FEBA-4E2C-A19F-4DCDF8409509",
        "type": "PointLight",
        "name": "PointLight",
        "castShadow": true,
        "layers": 1,
        "matrix": [1,0,0,0,0,1,0,0,0,0,1,0,10.364791,32.866141,1.198006,1],
        "color": 16744703,
        "intensity": 0.15,
        "distance": 0,
        "decay": 1,
        "shadow": {
          "camera": {
            "uuid": "C677301A-B911-43F0-9730-953C55B7F521",
            "type": "PerspectiveCamera",
            "layers": 1,
            "fov": 90,
            "zoom": 1,
            "near": 0.5,
            "far": 500,
            "focus": 10,
            "aspect": 1,
            "filmGauge": 35,
            "filmOffset": 0
          }
        }
      },
      {
        "uuid": "B0458740-A9C5-42CA-BE8E-DE43AB6FB056",
        "type": "PointLight",
        "name": "PointLight",
        "castShadow": true,
        "layers": 1,
        "matrix": [1,0,0,0,0,1,0,0,0,0,1,0,-22.338497,10.572159,4.585341,1],
        "color": 15486208,
        "intensity": 0.72,
        "distance": 0,
        "decay": 0.52,
        "shadow": {
          "camera": {
            "uuid": "CC0F72D7-805E-4A3E-900A-E8A4EC4DC327",
            "type": "PerspectiveCamera",
            "layers": 1,
            "fov": 90,
            "zoom": 1,
            "near": 0.5,
            "far": 500,
            "focus": 10,
            "aspect": 1,
            "filmGauge": 35,
            "filmOffset": 0
          }
        }
      }
    ],
    "background": 64
  }
}
